<?xml version="1.0"?>
<solitaire>
  <random>
    <card></card>
    <card></card>
    <card></card>
    <card></card>
    <card></card>
    <card></card>
    <card></card>
    <card></card>
    <card></card>
    <card></card>
    <card></card>
    <card></card>
    <card></card>
    <card></card>
    <card></card>
    <card></card>
    <card></card>
    <card></card>
    <card></card>
    <card></card>
    <card></card>
    <card></card>
    <card></card>
    <card></card>
  </random>
  <middle1>
    <card></card>
  </middle1>
  <middle2>
    <card></card>
    <card></card>
  </middle2>
  <middle3>
    <card></card>
    <card></card>
    <card></card>
  </middle3>
  <middle4>
    <card></card>
    <card></card>
    <card></card>
    <card></card>
  </middle4>
  <middle5>
    <card></card>
    <card></card>
    <card></card>
    <card></card>
    <card></card>
  </middle5>
  <middle6>
    <card></card>
    <card></card>
    <card></card>
    <card></card>
    <card></card>
    <card></card>
  </middle6>
  <middle7>
    <card></card>
    <card></card>
    <card></card>
    <card></card>
    <card></card>
    <card></card>
    <card></card>
  </middle7>
</solitaire>